{"_type":"export","__export_format":4,"__export_date":"2019-08-22T01:21:56.771Z","__export_source":"insomnia.desktop.app:v6.6.2","resources":[{"_id":"req_f84624dad6a441258febf0c1d68f746d","authentication":{},"body":{"mimeType":"application/json","text":"{ \n\t\"title\": \"Novo Título\"\n}"},"created":1566435093518,"description":"","headers":[{"id":"pair_deb7ec27eddf487088be3f1a37defdf1","name":"Content-Type","value":"application/json"}],"isPrivate":false,"metaSortKey":-1566435093518,"method":"PUT","modified":1566435133648,"name":"Altera Título do Projeto","parameters":[],"parentId":"wrk_263922430aaa4fbdbfe662fb21c2ac9a","settingDisableRenderRequestBody":false,"settingEncodeUrl":true,"settingRebuildPath":true,"settingSendCookies":true,"settingStoreCookies":true,"url":"http://localhost:3000/projects/1","_type":"request"},{"_id":"wrk_263922430aaa4fbdbfe662fb21c2ac9a","created":1566433233401,"description":"","modified":1566433261998,"name":"Desafio 01","parentId":null,"_type":"workspace"},{"_id":"req_0f37e2edc082407abbda188148b63f0b","authentication":{},"body":{},"created":1566435069133,"description":"","headers":[],"isPrivate":false,"metaSortKey":-1566435069133,"method":"DELETE","modified":1566435106745,"name":"Deleta Projeto","parameters":[],"parentId":"wrk_263922430aaa4fbdbfe662fb21c2ac9a","settingDisableRenderRequestBody":false,"settingEncodeUrl":true,"settingRebuildPath":true,"settingSendCookies":true,"settingStoreCookies":true,"url":"http://localhost:3000/projects/1","_type":"request"},{"_id":"req_48b24e42db0d4d5b87514e350e009ee0","authentication":{},"body":{},"created":1566434070368,"description":"","headers":[],"isPrivate":false,"metaSortKey":-1566434070368,"method":"GET","modified":1566434076711,"name":"Listagem de projetos","parameters":[],"parentId":"wrk_263922430aaa4fbdbfe662fb21c2ac9a","settingDisableRenderRequestBody":false,"settingEncodeUrl":true,"settingRebuildPath":true,"settingSendCookies":true,"settingStoreCookies":true,"url":"http://localhost:3000/projects","_type":"request"},{"_id":"req_f49ad6b63cab421bbc128dddd224aa65","authentication":{},"body":{"mimeType":"application/json","text":"{ \n\t\"id\": \"1\",\n\t\"title\": \"Novo Projeto\",\n\t\"tasks\": []\n}"},"created":1566433288914,"description":"","headers":[{"id":"pair_672a2ffc338b49bdb84889736b788e90","name":"Content-Type","value":"application/json"}],"isPrivate":false,"metaSortKey":-1566433981566,"method":"POST","modified":1566433992324,"name":"Cadastra Projeto","parameters":[],"parentId":"wrk_263922430aaa4fbdbfe662fb21c2ac9a","settingDisableRenderRequestBody":false,"settingEncodeUrl":true,"settingRebuildPath":true,"settingSendCookies":true,"settingStoreCookies":true,"url":"http://localhost:3000/projects","_type":"request"},{"_id":"req_c368a7e5b8684a949994a63b3357f6b3","authentication":{},"body":{"mimeType":"application/json","text":"{ \n\t\"title\": \"Nova Tarefa\"\n}"},"created":1566434088117,"description":"","headers":[{"id":"pair_672a2ffc338b49bdb84889736b788e90","name":"Content-Type","value":"application/json"}],"isPrivate":false,"metaSortKey":-1566430640589,"method":"POST","modified":1566434130071,"name":"Cadastra Tarefa","parameters":[],"parentId":"wrk_263922430aaa4fbdbfe662fb21c2ac9a","settingDisableRenderRequestBody":false,"settingEncodeUrl":true,"settingRebuildPath":true,"settingSendCookies":true,"settingStoreCookies":true,"url":"http://localhost:3000/projects/1/tasks","_type":"request"},{"_id":"env_52fcc34239df1d70b59d1ac1d43e99ddabad6eda","color":null,"created":1566433233444,"data":{},"dataPropertyOrder":null,"isPrivate":false,"metaSortKey":1566433233444,"modified":1566433233444,"name":"Base Environment","parentId":"wrk_263922430aaa4fbdbfe662fb21c2ac9a","_type":"environment"},{"_id":"jar_52fcc34239df1d70b59d1ac1d43e99ddabad6eda","cookies":[],"created":1566433233449,"modified":1566433233449,"name":"Default Jar","parentId":"wrk_263922430aaa4fbdbfe662fb21c2ac9a","_type":"cookie_jar"}]}